dmem.v
module dmem (
	input         clk  ,
	input         we   ,
	input  [31:0] addr ,
	input  [31:0] wdata,
	output [31:0] rdata
);

	reg [31:0] rdata;

	reg [31:0] memdata[63:0];

	initial
	begin
		memdata[0]=5;//n
		memdata[1]=0; //sum

		// array
		memdata[2] = 1;
		memdata[3]=2;
		memdata[4] =3;
		memdata[5] =4;
		memdata[6] = 5;
	end

	always @(memdata[addr]) begin
		rdata = memdata[addr];
	end

	always @(negedge clk) begin
		if(1'b1 == we) begin
			$display("xxxxxxxxxxxxxxxxxxxxxxxxxxxxxxxxxxxxxxxxxxxxxxxxxxxxxxxxxxxxxxxxxxxxxxxxx %d", addr);
			memdata[addr] = wdata;
		end
	end

	initial
	begin
		$monitor("Data: n:%d, sum:%d, a[0]:%d, a[1]:%d, a[2]:%d, a[3]:%d, a[4]:%d",
		memdata[0], memdata[1], memdata[2], memdata[3],
		memdata[4], memdata[5], memdata[6]);
	end
endmodule

sign_extend.v
module sign_extend (
	input  [15:0] idata,
	output [31:0] odata
);

	reg [31:0] odata;

	always @(idata) begin : proc_sign_extend
		odata = {{16{idata[15]}}, idata};
	end

	always @(idata)
	begin
		$display("Sign extend input: %b", idata);
		#1 $display("Sign extend output: %b", odata);
	end

endmodule

alu.v
module alu (
    input  [31:0] a_in, b_in,
    input  [ 2:0] f_in ,
    output        zero,
    output        c_out,
    output [31:0] y_out
);

    wire [31:0] not_b_in;
    assign not_b_in = ~ b_in;

    wire [31:0] b_mux_not_b;
    assign b_mux_not_b = (1'b0 == f_in[2]) ? b_in : not_b_in;

    wire [31:0] fx00;
    assign fx00 = a_in & b_mux_not_b;

    wire [31:0] fx01;
    assign fx01 = a_in | b_mux_not_b;

    wire [31:0] fx10;
    assign {c_out, fx10} = a_in + b_mux_not_b + f_in[2];

    wire [31:0] fx11;
    assign fx11 = {{31{1'b0}}, ((a_in[31] == not_b_in[31]) && (fx10[31] != a_in[31])) ? ~(fx10[31]) : fx10[31]};

    assign zero = ~| y_out;

    assign y_out = 2'b00 == f_in[1:0] ? fx00 : (2'b01 == f_in[1:0] ? fx01 : (2'b10 == f_in[1:0] ? fx10 : fx11 ));
    always @(a_in or b_in or f_in)
    begin
        $display("Change in alu input: a_in:%d, b_in: %d, f_in:%d", a_in, b_in, f_in);
        #1 $display("Change in Result of alu: zero:%d, c_out:%d, y_out:%d", zero, c_out, y_out);
    end

endmodule

regfile.v
module regfile (
	input         clk  ,
	//
	input  [ 4:0] addr1,
	input  [ 4:0] addr2,
	input  reg_write   ,
	input  [ 4:0] addr3,
	input  [31:0] wdata,
	//
	output [31:0] data1,
	output [31:0] data2
);

	reg [31:0] regmem[31:0];
	reg [31:0] data1       ;
	reg [31:0] data2       ;

	always @(addr1 or regmem[addr1]) begin
		if (0 == addr1) begin
			data1 = 0;
		end
		else if(24 ==addr1)
		begin
			data1=0;
		end
		else begin
			data1 = regmem[addr1];
		end
	end

	always @(addr2 or regmem[addr2]) begin
		if (0 == addr2) begin
			data2 = 0;
		end
		else if(24 ==addr2)
		begin
			data2=0;
		end
		else begin
			data2 = regmem[addr2];
		end
	end

	always@ (negedge clk) begin
		if(1'b1 == reg_write) begin
			regmem[addr3] = wdata;
		end
	end

	always @(addr1 or addr2 or reg_write or addr3 or wdata)
	begin
		$display("Change in reg file input: addr1:%d, addr2:%d, addr3:%d, reg_write:%d, wdata:%d", addr1, addr2, addr3, reg_write, wdata);
		#1 $display("Output of the register file: data1:%d, data2:%d", data1, data2);
	end

	integer i;
	always @(posedge clk)
	begin
		for (i = 0; i < 11; i = i + 1)
		begin
			$display("reg %d: %d",i, regmem[i]);
		end
	end
endmodule

datapath.v
module datapath (
	input         clk       ,
	input         rst       ,
	input  [ 2:0] alucontrol,
	input         alu_src   ,
	input         branch    ,
	input         jump      ,
	input         mem_to_reg,
	input         reg_dst   ,
	input         reg_write ,
	// imem side
	input  [31:0] instr     ,
	output [31:0] pc        ,
	// dmem side
	input  [31:0] read_data ,
	output [31:0] alu_result,
	output [31:0] write_data
);

	wire [31:0] pc_plus_4;
	assign pc_plus_4 = pc + 4;

	wire [31:0] pc_jump;
	assign pc_jump = {pc_plus_4[31:28], instr[25:0], 2'b00};

	wire pc_src;
	assign pc_src = branch & zero;

	wire [31:0] pc_branch;
	assign pc_branch = pc_plus_4 + {imm_ext[29:0], 2'b00};

	wire [31:0] pc_next;
	assign pc_next = jump ? pc_jump : (pc_src ? pc_branch : pc_plus_4);

	reg [31:0] pc;
	always @(posedge clk)
	begin : proc_pc
		if(~rst)
		begin
			pc = pc_next;
		end
		else
		begin
			pc = 32'h00000000;
		end
	end

	always @pc
	begin
		$display("PC Changed to %d , time:%t", pc, $time);
	end

	wire [5:0] rt;
	assign rt = instr[20:16];

	wire [5:0] rd;
	assign rd = instr[15:11];

	wire [4:0] write_reg;
	assign write_reg = reg_dst ? rd : rt;

	wire [31:0] result;
	assign result = mem_to_reg ? read_data : alu_result ;

	wire [31:0] reg_data1;
	wire [31:0] reg_data2;

	regfile regfile_inst (
		.clk  (clk         ),
		.reg_write   (reg_write   ),
		.addr1(instr[25:21]),
		.addr2(instr[20:16]),
		.addr3(write_reg   ),
		.wdata(result      ),
		.data1(reg_data1   ),
		.data2(reg_data2   )
	);

	wire [31:0] src_a;
	wire [31:0] src_b;
	wire c_out;
	wire [31:0] alu_out;

	assign src_a = reg_data1;
	assign src_b = alu_src ? imm_ext : reg_data2;

	alu alu_inst (
		.a_in (src_a     ),
		.b_in (src_b     ),
		.f_in (alucontrol),
		.zero (zero      ),
		.c_out(c_out     ),
		.y_out(alu_out   )
	);
	assign alu_result = alu_out;

	wire [31:0] imm_ext;
	sign_extend sign_extend_inst (
		.idata(instr[15:0]),
		.odata(imm_ext    )
	);

	assign write_data = reg_data2;

endmodule

control_unit.v
module control_unit (
	input  [31:0] instr     ,
	// other side
	output        branch    ,
	output        jump      ,
	output        mem_to_reg,
	output        mem_write ,
	output        reg_dst   ,
	output        reg_write ,
	// alu side
	output [ 2:0] alucontrol,
	output        alu_src
);

	wire is_syscall;
	assign is_syscall = ((opcode == 6'b001100));
	wire [5:0] opcode;
	assign opcode = instr[31:26];

	wire [5:0] func;
	assign func = instr[5:0];

	wire is_add = ((opcode == 6'h00) & (func == 6'h20));
	wire is_sub = ((opcode == 6'h00) & (func == 6'h22));
	wire is_and = ((opcode == 6'h00) & (func == 6'h24));
	wire is_or  = ((opcode == 6'h00) & (func == 6'h25));
	wire is_slt = ((opcode == 6'h00) & (func == 6'h2A));

	wire is_lw = (opcode == 6'h23);
	wire is_sw = (opcode == 6'h2B);

	wire is_beq  = (opcode == 6'h04);
	wire is_addi = (opcode == 6'h08);
	wire is_j    = (opcode == 6'h02);

	assign branch     = is_beq;
	assign jump       = is_j;
	assign mem_to_reg = is_lw;
	assign mem_write  = is_sw;
	assign reg_dst    = is_add | is_sub | is_and | is_or | is_slt;
	assign reg_write  = is_add | is_sub | is_and | is_or | is_slt | is_addi | is_lw;
	assign alu_src    = is_addi | is_lw | is_sw;

	always @(opcode)
	begin
		if ( 6'b001100 == opcode)
		begin
			$finish;
		end
	end

	reg [2:0] alucontrol;

	always @(instr) begin
		casex ({instr[31:26], instr[5:0]})
			12'b000100xxxxxx : alucontrol = 3'b110;
			12'b001010xxxxxx : alucontrol = 3'b111;
			12'b001000xxxxxx : alucontrol = 3'b010;
			12'bxxxxxx100000 : alucontrol = 3'b010;
			12'bxxxxxx100010 : alucontrol = 3'b110;
			12'bxxxxxx100100 : alucontrol = 3'b000;
			12'bxxxxxx100101 : alucontrol = 3'b001;
			12'bxxxxxx101010 : alucontrol = 3'b111;
			default          : alucontrol = 3'b010;
		endcase
	end
	
	always @(instr)
    begin
        #1 $display("Output of the new instruction in controller: branch:%d, jump:%d, mem_to_reg:%d, mem_write:%d, reg_dst:%d, reg_write:%d, alucontrol:%b, alu_src:%d", branch, jump, mem_to_reg, mem_write, reg_dst, reg_write, alucontrol, alu_src);
    end

endmodule

mips.v
module mips (
    input         clk       ,
    input         rst       ,
    // imem side
    input  [31:0] imem_data ,
    output [31:0] imem_addr ,
    // dmem side
    input  [31:0] dmem_rdata,
    output        dmem_we   ,
    output [31:0] dmem_addr ,
    output [31:0] dmem_wdata
);

    wire [2:0] alucontrol;
    wire       alu_src   ;
    wire       branch    ;
    wire       jump      ;
    wire       mem_to_reg;
    wire       reg_dst   ;
    wire       reg_write ;

    control_unit controller_inst (
        .instr     (imem_data ),
        .alucontrol(alucontrol),
        .alu_src   (alu_src   ),
        .branch    (branch    ),
        .jump      (jump      ),
        .mem_to_reg(mem_to_reg),
        .mem_write (dmem_we ),
        .reg_dst   (reg_dst   ),
        .reg_write (reg_write )
    );

    datapath datapath_inst (
        .clk       (clk       ),
        .rst       (rst       ),
        .alucontrol(alucontrol),
        .alu_src   (alu_src   ),
        .branch    (branch    ),
        .jump      (jump      ),
        .mem_to_reg(mem_to_reg),
        .reg_dst   (reg_dst   ),
        .reg_write (reg_write ),
        .instr     (imem_data ),
        .pc        (imem_addr ),
        .read_data (dmem_rdata),
        .alu_result(dmem_addr ),
        .write_data(dmem_wdata)
    );

endmodule

imem.v
module imem (
	input  [ 7:0] addr,
	output [31:0] data
);

	reg [31:0] data;

	// r6 ith element
	// r1 index
	// r2 sum
	// r3 n (gp)
	// r5 address of ith element
	// r10 address of sum (gp +4)

	always @(addr) begin
		case(addr)
			//  addi r1 r0 0
			// op- 001000
			// rs- 00000
			// rt- 00001
			// i- 0000 0000 0000 0000
			00 : data = 32'b00100000000000010000000000000000;

			// addi r2 r0 0
			// op- 001000
			// rs- 00000
			// rt- 00010
			// i- 0000 0000 0000 0000
			04 : data = 32'b00100000000000100000000000000000;

			// addi r4 $gp 0
			// op- 001000
			// rt- 00100
			// rs- 11000
			// i-  0000 0000 0000 0000
			08 : data = 32'b00100011000001000000000000000000;

			// lw r3 r4
			// op- 100011
			// rt- 00011
			// rs- 00100
			// i- 0000 0000 0000 0000
			12 : data = 32'b10001100100000110000000000000000;

			// addi r5 $gp 8
			// op- 001000
			// rt- 00101
			// rs- 11000
			// i- 0000 0000 0000 1000
			16 : data = 32'b00100011000001010000000000001000;

			// addi r10 $gp 4
			// op- 001000
			// rt- 01010
			// rs- 11000
			// i-  0000 0000 0000 0100
			20 : data = 32'b00100011000010100000000000000100;

			// beq r1 r3 end
			// op- 000100
			// rs - 00001
			// rt - 00011
			// im - end-here-4
			24 : data = 32'b00010000001000110000000000000101;

			// lw r6 r5 0 
			// op-100011
			// rs-00101
			// rt-00110
			// i - 0
			28 : data = 32'b10001100101001100000000000000000;

			// add r2 r2 r6
			// op- 000000
			// rd-2 - 00010
			// rs-2 - 00010
			// rt-6 - 00110
			// shamt  - 00000
			// funct - 100000
			32 : data = 32'b00000000010000100011000000100000;

			// addi r5 r5 4
			// op - 001000
			// rt - 000101
			// rs - 000101
			// im - 4
			36 : data = 32'b00100000101001010000000000000100;

			//addi r1 r1 1
			// op - 001000
			// rt - 00001
			// rs - 00001
			// im - 00000000000000001
			40 : data = 32'b00100000001000010000000000000001;

			// beq r0 r0 
			// op - 000010
			// addr - start
			// 000010 000000000000000000110
			44 : data = 32'b00001000000000000000000000000110;

			//sw sum (gp +4)
			// op - 101011
			// rs - 01010
			// rt - 00110
			// imm - 4
			48 : data = 32'b10101101010001100000000000000100;

			// addi r4 r0 10 (argument for syscall)
			// op- 001000
			// rs- 00000
			// rt- 00100
			// i- 0000 0000 0000 1010
			52 : data = 32'b00100000000001000000000000001010;

			// syscall
			// op - 001100
			56 : data = 32'b00110000000000000000000000000000;
		endcase
	end
endmodule

main.v
module main (
	input clk, // clock
	input reset  // synchronous reset active high
);

	wire [31:0] imem_data ;
	wire [31:0] imem_addr ;
	wire [31:0] dmem_rdata;
	wire        dmem_we   ;
	wire [31:0] dmem_addr ;
	wire [31:0] dmem_wdata;

	imem imem_inst (
		.addr(imem_addr[7:0]),
		.data(imem_data     )
	);

	mips mips_inst (
		.clk       (clk       ),
		.rst       (reset     ),
		.imem_data (imem_data ),
		.imem_addr (imem_addr ),
		.dmem_rdata(dmem_rdata),
		.dmem_we   (dmem_we   ),
		.dmem_addr (dmem_addr ),
		.dmem_wdata(dmem_wdata)
	);

	dmem dmem_inst (
		.clk  (clk       ),
		.we   (dmem_we   ),
		.addr ({2'b0,dmem_addr[31:2]}),
		.wdata(dmem_wdata),
		.rdata(dmem_rdata)
	);

endmodule

tb.v
`resetall
// `timescale 1ns/10ps

`define CLKP 10 // clock period
`define CLKPDIV2 5 // clock period divided by 2

module tb;

    reg clock;
    reg reset;

    //clk, reset, pc, instr, aluout, writedata, memwrite, and readdata

    main main_circuit (.clk(clock), .reset(reset));

    // generate clock
    always begin
        #`CLKPDIV2 clock = ~clock;
    end

    initial begin
        $dumpfile("dump.vcd");
        $dumpvars(0, main_circuit);
    end

    initial begin
        // initialize all variables
        clock = 0; reset = 1;
        // wait for first negative edge before de-asserting reset
        @(negedge clock) reset = 0;
    end

endmodule

dump.vcd
$date
	Sat Jun 13 19:54:32 2020
$end
$version
	Icarus Verilog
$end
$timescale
	1s
$end
$scope module tb $end
$scope module main_circuit $end
$var wire 1 ! clk $end
$var wire 1 " reset $end
$var wire 32 # imem_data [31:0] $end
$var wire 32 $ imem_addr [31:0] $end
$var wire 1 % dmem_we $end
$var wire 32 & dmem_wdata [31:0] $end
$var wire 32 ' dmem_rdata [31:0] $end
$var wire 32 ( dmem_addr [31:0] $end
$scope module dmem_inst $end
$var wire 1 ! clk $end
$var wire 1 % we $end
$var wire 32 ) wdata [31:0] $end
$var wire 32 * addr [31:0] $end
$var reg 32 + rdata [31:0] $end
$upscope $end
$scope module imem_inst $end
$var wire 8 , addr [7:0] $end
$var reg 32 - data [31:0] $end
$upscope $end
$scope module mips_inst $end
$var wire 1 ! clk $end
$var wire 32 . dmem_rdata [31:0] $end
$var wire 32 / imem_data [31:0] $end
$var wire 1 " rst $end
$var wire 1 0 reg_write $end
$var wire 1 1 reg_dst $end
$var wire 1 2 mem_to_reg $end
$var wire 1 3 jump $end
$var wire 32 4 imem_addr [31:0] $end
$var wire 1 % dmem_we $end
$var wire 32 5 dmem_wdata [31:0] $end
$var wire 32 6 dmem_addr [31:0] $end
$var wire 1 7 branch $end
$var wire 3 8 alucontrol [2:0] $end
$var wire 1 9 alu_src $end
$scope module controller_inst $end
$var wire 32 : instr [31:0] $end
$var wire 1 0 reg_write $end
$var wire 1 1 reg_dst $end
$var wire 1 % mem_write $end
$var wire 1 2 mem_to_reg $end
$var wire 1 3 jump $end
$var wire 1 7 branch $end
$var wire 3 ; alucontrol [2:0] $end
$var wire 1 9 alu_src $end
$scope module aludec_inst $end
$var wire 32 < instr [31:0] $end
$var reg 3 = alucontrol [2:0] $end
$upscope $end
$scope module maindec_inst $end
$var wire 1 9 alu_src $end
$var wire 1 7 branch $end
$var wire 32 > instr [31:0] $end
$var wire 1 ? is_add $end
$var wire 1 @ is_and $end
$var wire 1 A is_or $end
$var wire 1 B is_slt $end
$var wire 1 C is_sub $end
$var wire 1 3 jump $end
$var wire 1 2 mem_to_reg $end
$var wire 1 % mem_write $end
$var wire 1 1 reg_dst $end
$var wire 1 0 reg_write $end
$var wire 6 D opcode [5:0] $end
$var wire 1 E is_syscall $end
$var wire 1 F is_sw $end
$var wire 1 G is_lw $end
$var wire 1 H is_j $end
$var wire 1 I is_beq $end
$var wire 1 J is_addi $end
$var wire 6 K func [5:0] $end
$upscope $end
$upscope $end
$scope module datapath_inst $end
$var wire 32 L alu_result [31:0] $end
$var wire 1 9 alu_src $end
$var wire 3 M alucontrol [2:0] $end
$var wire 1 7 branch $end
$var wire 1 ! clk $end
$var wire 32 N instr [31:0] $end
$var wire 1 3 jump $end
$var wire 1 2 mem_to_reg $end
$var wire 1 O pc_src $end
$var wire 32 P read_data [31:0] $end
$var wire 1 1 reg_dst $end
$var wire 1 0 reg_write $end
$var wire 1 " rst $end
$var wire 32 Q src_a [31:0] $end
$var wire 32 R write_data [31:0] $end
$var wire 1 S zero $end
$var wire 5 T write_reg [4:0] $end
$var wire 32 U src_b [31:0] $end
$var wire 6 V rt [5:0] $end
$var wire 32 W result [31:0] $end
$var wire 32 X reg_data2 [31:0] $end
$var wire 32 Y reg_data1 [31:0] $end
$var wire 6 Z rd [5:0] $end
$var wire 32 [ pc_plus_4 [31:0] $end
$var wire 32 \ pc_next [31:0] $end
$var wire 32 ] pc_jump [31:0] $end
$var wire 32 ^ pc_branch [31:0] $end
$var wire 32 _ imm_ext [31:0] $end
$var wire 1 ` c_out $end
$var wire 32 a alu_out [31:0] $end
$var reg 32 b pc [31:0] $end
$scope module alu_inst $end
$var wire 32 c a_in [31:0] $end
$var wire 32 d b_in [31:0] $end
$var wire 3 e f_in [2:0] $end
$var wire 32 f fx00 [31:0] $end
$var wire 32 g fx01 [31:0] $end
$var wire 32 h not_b_in [31:0] $end
$var wire 1 S zero $end
$var wire 32 i y_out [31:0] $end
$var wire 32 j fx11 [31:0] $end
$var wire 32 k fx10 [31:0] $end
$var wire 1 ` c_out $end
$var wire 32 l b_mux_not_b [31:0] $end
$upscope $end
$scope module regfile_inst $end
$var wire 5 m addr1 [4:0] $end
$var wire 5 n addr2 [4:0] $end
$var wire 5 o addr3 [4:0] $end
$var wire 1 ! clk $end
$var wire 1 0 reg_write $end
$var wire 32 p wdata [31:0] $end
$var reg 32 q data1 [31:0] $end
$var reg 32 r data2 [31:0] $end
$var integer 32 s i [31:0] $end
$upscope $end
$scope module sign_extend_inst $end
$var wire 16 t idata [15:0] $end
$var reg 32 u odata [31:0] $end
$scope begin proc_sign_extend $end
$upscope $end
$upscope $end
$scope begin proc_pc $end
$upscope $end
$upscope $end
$upscope $end
$upscope $end
$upscope $end
$enddefinitions $end
#0
$dumpvars
bx u
bx t
bx s
bx r
bx q
bx p
bx o
bx n
bx m
bx l
bx k
b0x j
bx i
bx h
bx g
bx f
bx e
bx d
bx c
bx b
bx a
x`
bx _
bx ^
bx00 ]
bx \
bx [
b0xxxxx Z
bx Y
bx X
bx W
b0xxxxx V
bx U
bx T
xS
bx R
bx Q
bx P
xO
bx N
bx M
bx L
bx K
xJ
xI
xH
xG
xF
xE
bx D
xC
xB
xA
x@
x?
bx >
bx =
bx <
bx ;
bx :
x9
bx 8
x7
bx 6
bx 5
bx 4
x3
x2
x1
x0
bx /
bx .
bx -
bx ,
bx +
bx *
bx )
bx (
bx '
bx &
x%
bx $
bx #
1"
0!
$end
#5
b0 W
b0 p
b101 '
b101 +
b101 .
b101 P
b0 j
1S
b0 (
b0 *
b0 6
b0 L
b0 a
b0 i
01
b0 k
0`
b0 g
b100 \
b11111111111111111111111111111111 h
b0 l
b1 T
b1 o
b0 f
b0 U
b0 d
b100 ^
10
19
0O
0?
0C
0@
0A
0B
b0 Q
b0 c
b0 Y
b0 q
b0 _
b0 u
b10 8
b10 ;
b10 =
b10 M
b10 e
02
0G
0%
0F
07
0I
1J
03
0H
0E
b1000 D
b0 K
b1 V
b0 Z
b0 m
b1 n
b0 t
b100000000000010000000000000000 #
b100000000000010000000000000000 -
b100000000000010000000000000000 /
b100000000000010000000000000000 :
b100000000000010000000000000000 <
b100000000000010000000000000000 >
b100000000000010000000000000000 N
b1000000000000000000 ]
b0 ,
b100 [
b0 $
b0 4
b0 b
b1011 s
1!
#10
b0 &
b0 )
b0 5
b0 R
b0 X
b0 r
0"
0!
#15
b10 T
b10 o
bx &
bx )
bx 5
bx R
bx X
bx r
b10000000000000000000 ]
b10 V
b10 n
b1000 \
b100000000000100000000000000000 #
b100000000000100000000000000000 -
b100000000000100000000000000000 /
b100000000000100000000000000000 :
b100000000000100000000000000000 <
b100000000000100000000000000000 >
b100000000000100000000000000000 N
b100 ,
b1000 ^
b1000 [
b100 $
b100 4
b100 b
b1011 s
1!
#20
b0 &
b0 )
b0 5
b0 R
b0 X
b0 r
0!
#25
b100 T
b100 o
bx &
bx )
bx 5
bx R
bx X
bx r
b1100000100000000000000000000 ]
b100 V
b11000 m
b100 n
b1100 \
b100011000001000000000000000000 #
b100011000001000000000000000000 -
b100011000001000000000000000000 /
b100011000001000000000000000000 :
b100011000001000000000000000000 <
b100011000001000000000000000000 >
b100011000001000000000000000000 N
b1000 ,
b1100 ^
b1100 [
b1000 $
b1000 4
b1000 b
b1011 s
1!
#30
b0 &
b0 )
b0 5
b0 R
b0 X
b0 r
0!
#35
b11 T
b11 o
b101 W
b101 p
bx &
bx )
bx 5
bx R
bx X
bx r
12
1G
0J
b100011 D
b10000011000000000000000000 ]
b11 V
b100 m
b11 n
b10000 \
b10001100100000110000000000000000 #
b10001100100000110000000000000000 -
b10001100100000110000000000000000 /
b10001100100000110000000000000000 :
b10001100100000110000000000000000 <
b10001100100000110000000000000000 >
b10001100100000110000000000000000 N
b1100 ,
b10000 ^
b10000 [
b1100 $
b1100 4
b1100 b
b1011 s
1!
#40
b101 &
b101 )
b101 5
b101 R
b101 X
b101 r
0!
#45
bx '
bx +
bx .
bx P
0S
b1000 (
b1000 *
b1000 6
b1000 L
b1000 a
b1000 i
b1000 k
b1000 g
b11111111111111111111111111110111 h
b1000 l
b101 T
b101 o
b1000 U
b1000 d
b1000 W
b1000 p
bx &
bx )
bx 5
bx R
bx X
bx r
b1000 _
b1000 u
02
0G
1J
b1000 D
b1000 K
b1100000101000000000000100000 ]
b101 V
b11000 m
b101 n
b1000 t
b10100 \
b100011000001010000000000001000 #
b100011000001010000000000001000 -
b100011000001010000000000001000 /
b100011000001010000000000001000 :
b100011000001010000000000001000 <
b100011000001010000000000001000 >
b100011000001010000000000001000 N
b10000 ,
b110100 ^
b10100 [
b10000 $
b10000 4
b10000 b
b1011 s
1!
#50
b1000 &
b1000 )
b1000 5
b1000 R
b1000 X
b1000 r
0!
#55
b100 W
b100 p
b11 '
b11 +
b11 .
b11 P
b100 (
b100 *
b100 6
b100 L
b100 a
b100 i
b100 k
b100 g
b11111111111111111111111111111011 h
b100 l
b1010 T
b1010 o
b100 U
b100 d
bx &
bx )
bx 5
bx R
bx X
bx r
b100 _
b100 u
b100 K
b1100001010000000000000010000 ]
b1010 V
b1010 n
b100 t
b11000 \
b100011000010100000000000000100 #
b100011000010100000000000000100 -
b100011000010100000000000000100 /
b100011000010100000000000000100 :
b100011000010100000000000000100 <
b100011000010100000000000000100 >
b100011000010100000000000000100 N
b10100 ,
b101000 ^
b11000 [
b10100 $
b10100 4
b10100 b
b1011 s
1!
#60
b100 &
b100 )
b100 5
b100 R
b100 X
b100 r
0!
#65
b11111111111111111111111111111011 W
b11111111111111111111111111111011 p
bx '
bx +
bx .
bx P
b1 j
b11111111111111111111111111111011 (
b11111111111111111111111111111011 *
b11111111111111111111111111111011 6
b11111111111111111111111111111011 L
b11111111111111111111111111111011 a
b11111111111111111111111111111011 i
b11111111111111111111111111111010 g
b11111111111111111111111111111010 h
b11111111111111111111111111111010 l
b11111111111111111111111111111011 k
09
00
b11 T
b11 o
b101 U
b101 d
b101 &
b101 )
b101 5
b101 R
b101 X
b101 r
b101 _
b101 u
b110 8
b110 ;
b110 =
b110 M
b110 e
17
1I
0J
b100 D
b101 K
b100011000000000000010100 ]
b11 V
b1 m
b11 n
b101 t
b11100 \
b10000001000110000000000000101 #
b10000001000110000000000000101 -
b10000001000110000000000000101 /
b10000001000110000000000000101 :
b10000001000110000000000000101 <
b10000001000110000000000000101 >
b10000001000110000000000000101 N
b11000 ,
b110000 ^
b11100 [
b11000 $
b11000 4
b11000 b
b1011 s
1!
#70
0!
#75
bx '
bx +
bx .
bx P
b1000 (
b1000 *
b1000 6
b1000 L
b1000 a
b1000 i
b1000 g
b0 j
b0 l
b11111111111111111111111111111111 h
19
b110 T
b110 o
b0 f
b1000 k
0`
b0 U
b0 d
10
bx W
bx p
b1000 Q
b1000 c
b1000 Y
b1000 q
bx &
bx )
bx 5
bx R
bx X
bx r
b0 _
b0 u
b10 8
b10 ;
b10 =
b10 M
b10 e
12
1G
07
0I
b100011 D
b0 K
b10100110000000000000000000 ]
b110 V
b101 m
b110 n
b0 t
b100000 \
b10001100101001100000000000000000 #
b10001100101001100000000000000000 -
b10001100101001100000000000000000 /
b10001100101001100000000000000000 :
b10001100101001100000000000000000 <
b10001100101001100000000000000000 >
b10001100101001100000000000000000 N
b11100 ,
b100000 ^
b100000 [
b11100 $
b11100 4
b11100 b
b1011 s
1!
#80
0!
#85
b101 '
b101 +
b101 .
b101 P
11
1S
b0 (
b0 *
b0 6
b0 L
b0 a
b0 i
b11111111111111111111111111111111 h
b0 l
09
b110 T
b110 o
b0 g
b0 k
b0 U
b0 d
10
b0 W
b0 p
1?
b0 Q
b0 c
b0 Y
b0 q
b0 &
b0 )
b0 5
b0 R
b0 X
b0 r
b11000000100000 _
b11000000100000 u
02
0G
b0 D
b100000 K
b1000010001100000010000000 ]
b10 V
b110 Z
b10 m
b10 n
b11000000100000 t
b100100 \
b10000100011000000100000 #
b10000100011000000100000 -
b10000100011000000100000 /
b10000100011000000100000 :
b10000100011000000100000 <
b10000100011000000100000 >
b10000100011000000100000 N
b100000 ,
b1100000010100100 ^
b100100 [
b100000 $
b100000 4
b100000 b
b1011 s
1!
#90
0!
#95
b1100 W
b1100 p
bx '
bx +
bx .
bx P
01
0S
b1100 (
b1100 *
b1100 6
b1100 L
b1100 a
b1100 i
b0 f
b11111111111111111111111111111011 h
b100 l
19
b101 T
b101 o
b1100 g
b1100 k
b100 U
b100 d
0?
b1000 Q
b1000 c
b1000 Y
b1000 q
b1000 &
b1000 )
b1000 5
b1000 R
b1000 X
b1000 r
b100 _
b100 u
1J
b1000 D
b100 K
b10100101000000000000010000 ]
b101 V
b0 Z
b101 m
b101 n
b100 t
b101000 \
b100000101001010000000000000100 #
b100000101001010000000000000100 -
b100000101001010000000000000100 /
b100000101001010000000000000100 :
b100000101001010000000000000100 <
b100000101001010000000000000100 >
b100000101001010000000000000100 N
b100100 ,
b111000 ^
b101000 [
b100100 $
b100100 4
b100100 b
b1011 s
1!
#100
b10000 W
b10000 p
b10000 (
b10000 *
b10000 6
b10000 L
b10000 a
b10000 i
b100 f
b10000 k
b1100 Q
b1100 c
b1100 Y
b1100 q
b1100 &
b1100 )
b1100 5
b1100 R
b1100 X
b1100 r
0!
#105
b1 W
b1 p
b0 '
b0 +
b0 .
b0 P
b1 (
b1 *
b1 6
b1 L
b1 a
b1 i
b11111111111111111111111111111110 h
b1 l
b1 T
b1 o
b0 f
b1 g
b1 k
b1 U
b1 d
b0 Q
b0 c
b0 Y
b0 q
b0 &
b0 )
b0 5
b0 R
b0 X
b0 r
b1 _
b1 u
b1 K
b100001000000000000000100 ]
b1 V
b1 m
b1 n
b1 t
b101100 \
b100000001000010000000000000001 #
b100000001000010000000000000001 -
b100000001000010000000000000001 /
b100000001000010000000000000001 :
b100000001000010000000000000001 <
b100000001000010000000000000001 >
b100000001000010000000000000001 N
b101000 ,
b110000 ^
b101100 [
b101000 $
b101000 4
b101000 b
b1011 s
1!
#110
b10 W
b10 p
b1 '
b1 +
b1 .
b1 P
b10 (
b10 *
b10 6
b10 L
b10 a
b10 i
b1 f
b10 k
b1 Q
b1 c
b1 Y
b1 q
b1 &
b1 )
b1 5
b1 R
b1 X
b1 r
0!
#115
1S
b0 W
b0 p
b101 '
b101 +
b101 .
b101 P
b0 (
b0 *
b0 6
b0 L
b0 a
b0 i
b0 g
b11111111111111111111111111111111 h
b0 l
09
00
b0 T
b0 o
b0 f
b0 k
b0 U
b0 d
b0 Q
b0 c
b0 Y
b0 q
b0 &
b0 )
b0 5
b0 R
b0 X
b0 r
b110 _
b110 u
0J
13
1H
b10 D
b110 K
b11000 ]
b0 V
b0 m
b0 n
b110 t
b11000 \
b1000000000000000000000000110 #
b1000000000000000000000000110 -
b1000000000000000000000000110 /
b1000000000000000000000000110 :
b1000000000000000000000000110 <
b1000000000000000000000000110 >
b1000000000000000000000000110 N
b101100 ,
b1001000 ^
b110000 [
b101100 $
b101100 4
b101100 b
b1011 s
1!
#120
0!
#125
b1 j
b11111111111111111111111111111100 W
b11111111111111111111111111111100 p
bx '
bx +
bx .
bx P
0S
b11111111111111111111111111111100 (
b11111111111111111111111111111100 *
b11111111111111111111111111111100 6
b11111111111111111111111111111100 L
b11111111111111111111111111111100 a
b11111111111111111111111111111100 i
0`
b0 f
b11111111111111111111111111111010 h
b11111111111111111111111111111010 l
b11 T
b11 o
b11111111111111111111111111111011 g
b11111111111111111111111111111100 k
b101 U
b101 d
0O
b11100 \
b1 Q
b1 c
b1 Y
b1 q
b101 &
b101 )
b101 5
b101 R
b101 X
b101 r
b101 _
b101 u
b110 8
b110 ;
b110 =
b110 M
b110 e
17
1I
03
0H
b100 D
b101 K
b100011000000000000010100 ]
b11 V
b1 m
b11 n
b101 t
b10000001000110000000000000101 #
b10000001000110000000000000101 -
b10000001000110000000000000101 /
b10000001000110000000000000101 :
b10000001000110000000000000101 <
b10000001000110000000000000101 >
b10000001000110000000000000101 N
b11000 ,
b110000 ^
b11100 [
b11000 $
b11000 4
b11000 b
b1011 s
1!
#130
0!
